spectral_neural_nets
