Metadata-Version: 2.1
Name: spectral-neural-nets
Version: 0.0.3
Summary: spectral_neural_nets
Home-page: https://github.com/lukewood/spectral-neural-nets
Author: Luke Wood
Author-email: lukewoodcs@gmail.com
License: UNKNOWN
Platform: UNKNOWN
